{
  "table_name": "location_gmaps_static",
  "full_table_id": "ledger-fcc1e.trb_pymnts_derived.location_gmaps_static",
  "total_columns": 16,
  "sample_rows_analyzed": 10000,
  "documentation_generated": "2026-05-06 11:47:02.012145",
  "columns": [
    {
      "column_name": "phone_number",
      "data_type": "STRING",
      "nullable": true,
      "null_percentage": 0.0,
      "description": "Merchant phone number (10-11 digit Indonesian mobile, no country code prefix). Primary key for merchant identification.",
      "business_context": "Required field - always populated",
      "example_values": [
        "85314173200",
        "81237897255",
        "83116081741"
      ]
    },
    {
      "column_name": "lat_long",
      "data_type": "STRING",
      "nullable": true,
      "null_percentage": 0.0,
      "description": "Geographic location field derived from geocoding API.",
      "business_context": "Required field - always populated",
      "example_values": [
        "5.391094208,95.91785431",
        "-8.6740059,115.1728238",
        "-8.0965327,115.1569949"
      ]
    },
    {
      "column_name": "latitude",
      "data_type": "STRING",
      "nullable": true,
      "null_percentage": 0.0,
      "description": "Geographic location field derived from geocoding API.",
      "business_context": "Required field - always populated",
      "example_values": [
        "5.391094208",
        "-8.6740059",
        "-8.0965327"
      ]
    },
    {
      "column_name": "longitude",
      "data_type": "STRING",
      "nullable": true,
      "null_percentage": 0.0,
      "description": "Geographic location field derived from geocoding API.",
      "business_context": "Required field - always populated",
      "example_values": [
        "95.91785431",
        "115.1728238",
        "115.1569949"
      ]
    },
    {
      "column_name": "formatted_address",
      "data_type": "STRING",
      "nullable": true,
      "null_percentage": 0.0,
      "description": "Geographic location field derived from geocoding API.",
      "business_context": "Required field - always populated",
      "example_values": [
        "9WR9+C5J, Seukeumbrok, Kec. Pidie, Kabupaten Pidie, Aceh, Indonesia",
        "Jl. Gn. Tangkuban Perahu No.10a, Kerobokan Kelod, Kec. Kuta Utara, Kabupaten Badung, Bali 80361, Ind",
        "W534+9QG, Jl. Bungkulan, Bungkulan, Kec. Sawan, Kabupaten Buleleng, Bali 81171, Indonesia"
      ]
    },
    {
      "column_name": "raw_response",
      "data_type": "STRING",
      "nullable": true,
      "null_percentage": 100.0,
      "description": "Empty column - no sample data available",
      "business_context": "Optional field - sparsely populated",
      "example_values": []
    },
    {
      "column_name": "timestamp__",
      "data_type": "TIMESTAMP",
      "nullable": true,
      "null_percentage": 0.0,
      "description": "Date/time field.",
      "business_context": "Required field - always populated",
      "example_values": [
        "2026-03-06 06:00:06.308148+00:00",
        "2026-03-06 06:00:06.308148+00:00",
        "2026-03-06 06:00:06.308148+00:00"
      ],
      "possible_values": [
        "2026-01-16 07:00:08.907528+00:00",
        "2026-02-27 03:50:29.076038+00:00",
        "2026-03-06 06:00:06.308148+00:00"
      ]
    },
    {
      "column_name": "source_flag",
      "data_type": "STRING",
      "nullable": true,
      "null_percentage": 0.0,
      "description": "Source Flag field",
      "business_context": "Required field - always populated",
      "example_values": [
        "Mar 2026",
        "Mar 2026",
        "Mar 2026"
      ],
      "possible_values": [
        "Feb 2026",
        "Jan 2026",
        "Mar 2026"
      ]
    },
    {
      "column_name": "old_kecamatan_dont_use",
      "data_type": "STRING",
      "nullable": true,
      "null_percentage": 0.04,
      "description": "Old Kecamatan Dont Use field",
      "business_context": "Core field - rarely empty (>90% populated)",
      "example_values": [
        "SEUKEUMBROK",
        "KEC. KUTA UTARA",
        "KEC. SAWAN"
      ]
    },
    {
      "column_name": "old_kabupaten_dont_use",
      "data_type": "STRING",
      "nullable": true,
      "null_percentage": 0.0,
      "description": "Old Kabupaten Dont Use field",
      "business_context": "Required field - always populated",
      "example_values": [
        "PIDIE",
        "KABUPATEN BADUNG",
        "KABUPATEN BULELENG"
      ]
    },
    {
      "column_name": "old_province_dont_use",
      "data_type": "STRING",
      "nullable": true,
      "null_percentage": 0.0,
      "description": "Old Province Dont Use field",
      "business_context": "Required field - always populated",
      "example_values": [
        "ACEH",
        "BALI",
        "BALI"
      ]
    },
    {
      "column_name": "kabupaten",
      "data_type": "STRING",
      "nullable": true,
      "null_percentage": 0.0,
      "description": "Kabupaten field",
      "business_context": "Required field - always populated",
      "example_values": [
        "KABUPATEN PIDIE",
        "KABUPATEN BADUNG",
        "KABUPATEN BULELENG"
      ]
    },
    {
      "column_name": "kecamatan",
      "data_type": "STRING",
      "nullable": true,
      "null_percentage": 0.0,
      "description": "Kecamatan field",
      "business_context": "Required field - always populated",
      "example_values": [
        "PIDIE",
        "KUTA UTARA",
        "SAWAN"
      ]
    },
    {
      "column_name": "province",
      "data_type": "STRING",
      "nullable": true,
      "null_percentage": 0.0,
      "description": "Province field",
      "business_context": "Required field - always populated",
      "example_values": [
        "NANGGROE ACEH DARUSSALAM",
        "BALI",
        "BALI"
      ]
    },
    {
      "column_name": "area",
      "data_type": "STRING",
      "nullable": true,
      "null_percentage": 0.0,
      "description": "Area field",
      "business_context": "Required field - always populated",
      "example_values": [
        "SUMATERA 1",
        "BALI NUSRA",
        "BALI NUSRA"
      ],
      "possible_values": [
        "BALI NUSRA",
        "JAKARTA",
        "JAVA 1",
        "JAVA 2",
        "JAVA 3",
        "KALIMANTAN",
        "SULAWESI",
        "SUMATERA 1",
        "SUMATERA 2",
        "SUMATERA 3"
      ]
    },
    {
      "column_name": "parsing_status",
      "data_type": "STRING",
      "nullable": true,
      "null_percentage": 0.0,
      "description": "Status or state field.",
      "business_context": "Required field - always populated",
      "example_values": [
        "COMPLETE_HIGH_CONFIDENCE",
        "COMPLETE_HIGH_CONFIDENCE",
        "COMPLETE_HIGH_CONFIDENCE"
      ],
      "possible_values": [
        "COMPLETE_HIGH_CONFIDENCE",
        "COMPLETE_LOW_CONFIDENCE",
        "COMPLETE_MEDIUM_CONFIDENCE"
      ]
    }
  ]
}